<refsect1>
<programlisting>
<emphasis role="csdtag">&lt;CsoundSynthesizer&gt;</emphasis>
<emphasis role="csdtag">&lt;CsOptions&gt;</emphasis>
<emphasis role="comment">; Select audio/midi flags here according to platform</emphasis>
<emphasis role="comment">; Audio out   Audio in</emphasis>
-odac    <emphasis role="comment">;;;RT audio I/O</emphasis>
<emphasis role="comment">; For Non-realtime ouput leave only the line below:</emphasis>
<emphasis role="comment">; -o pvsadsyn.wav -W ;;; for file output any platform</emphasis>
<emphasis role="csdtag">&lt;/CsOptions&gt;</emphasis>
<emphasis role="csdtag">&lt;CsInstruments&gt;</emphasis>

<emphasis role="ohdr">sr</emphasis> <emphasis role="op">=</emphasis> 44100
<emphasis role="ohdr">ksmps</emphasis> <emphasis role="op">=</emphasis> 16
<emphasis role="ohdr">nchnls</emphasis> <emphasis role="op">=</emphasis> 1
<emphasis role="ohdr">0dbfs</emphasis> <emphasis role="op">=</emphasis> 1

<emphasis role="comment">;; example written by joachim heintz 2009</emphasis>

<emphasis role="oblock">opcode</emphasis> FileToPvsBuf, iik, Siiii
<emphasis role="comment">;;writes an audio file at the first k-cycle to a fft-buffer (via pvsbuffer)</emphasis>
Sfile, ifftsize, ioverlap, iwinsize, iwinshape <emphasis role="opc">xin</emphasis>
ktimek		<emphasis role="opc">timeinstk</emphasis>
<emphasis role="octrl">if</emphasis> ktimek <emphasis role="op">==</emphasis> 1 then
ilen		<emphasis role="opc">filelen</emphasis>	Sfile
kcycles	<emphasis role="op">=</emphasis>		ilen <emphasis role="op">*</emphasis> <emphasis role="ohdr">kr</emphasis><emphasis role="comment">; number of k-cycles to write the fft-buffer</emphasis>
kcount		<emphasis role="opc">init</emphasis>		0
<emphasis role="olabel">loop</emphasis><emphasis role="op">:</emphasis>
ain		<emphasis role="opc">soundin</emphasis>	Sfile
fftin		<emphasis role="opc">pvsanal</emphasis>	ain, ifftsize, ioverlap, iwinsize, iwinshape
ibuf, ktim	<emphasis role="opc">pvsbuffer</emphasis>	fftin, ilen <emphasis role="op">+</emphasis> (ifftsize <emphasis role="op">/</emphasis> sr)
		<emphasis role="octrl">loop_lt</emphasis>	kcount, 1, kcycles, <emphasis role="olabel">loop</emphasis>
		<emphasis role="opc">xout</emphasis>		ibuf, ilen, ktim
<emphasis role="octrl">endif</emphasis>
<emphasis role="oblock">endop</emphasis>


<emphasis role="oblock">instr</emphasis> 1
istretch	<emphasis role="op">=</emphasis>		p4<emphasis role="comment">; time stretching factor</emphasis>
ifftsize	<emphasis role="op">=</emphasis>		1024
ioverlap	<emphasis role="op">=</emphasis>		ifftsize <emphasis role="op">/</emphasis> 4
iwinsize	<emphasis role="op">=</emphasis>		ifftsize
iwinshape	<emphasis role="op">=</emphasis>		1<emphasis role="comment">; von-Hann window</emphasis>
ibuffer, ilen, k0		FileToPvsBuf	"fox.wav", ifftsize, ioverlap, iwinsize, iwinshape
p3		<emphasis role="op">=</emphasis>		istretch <emphasis role="op">*</emphasis> ilen<emphasis role="comment">; set p3 to the correct value</emphasis>
ktmpnt		<emphasis role="opc">linseg</emphasis>		0, p3, ilen<emphasis role="comment">; time pointer</emphasis>
fread 		<emphasis role="opc">pvsbufread</emphasis>  	ktmpnt, ibuffer<emphasis role="comment">; read the buffer</emphasis>
aout		<emphasis role="opc">pvsadsyn</emphasis>	fread, 10, 1<emphasis role="comment">; resynthesis with the first 10 bins</emphasis>
		<emphasis role="opc">out</emphasis>		aout
<emphasis role="oblock">endin</emphasis>

<emphasis role="csdtag">&lt;/CsInstruments&gt;</emphasis>
<emphasis role="csdtag">&lt;CsScore&gt;</emphasis>
<emphasis role="stamnt">i</emphasis> 1 0 1 20
<emphasis role="stamnt">e</emphasis>
<emphasis role="csdtag">&lt;/CsScore&gt;</emphasis>
<emphasis role="csdtag">&lt;/CsoundSynthesizer&gt;</emphasis>
</programlisting>
</refsect1>